{
  "schemaVersion": 1,
  "reportId": "apollo-1524705623793347474-1783328254688-hek8t7qn",
  "generatedAt": "2026-07-06T08:57:34.688Z",
  "suggestedFileName": "Darina-Vinogradova_06-07-2026_11-57-34.json",
  "user": {
    "id": "1524705623793347474",
    "name": "Darina Vinogradova",
    "slug": "Darina-Vinogradova"
  },
  "plugin": {
    "name": "Apollo",
    "version": "0.1.38"
  },
  "figma": {
    "fileKey": null,
    "fileName": "Валютное хеджирование",
    "editorType": "figma"
  },
  "scan": {
    "channel": "Desktop",
    "startedAt": "2026-07-06T08:57:21.031Z",
    "finishedAt": "2026-07-06T08:57:34.688Z",
    "durationMs": 13657,
    "selection": [
      {
        "nodeId": "58613:29289",
        "name": "[M] WidjetAdvice",
        "nodeType": "COMPONENT_SET",
        "path": "[M] WidjetAdvice",
        "componentKey": null
      }
    ],
    "settings": {
      "shellAuditEnabled": false
    }
  },
  "summary": {
    "scannedComponents": 33,
    "problemOccurrenceCount": 41,
    "categoryCounts": {
      "deprecatedComponents": 0,
      "deprecatedStyles": 0,
      "customStyles": 13,
      "updates": 0,
      "customizations": 9,
      "localComponents": 3,
      "detachedComponents": 0,
      "presets": 0,
      "technicalComponents": 0,
      "currentComponents": 15,
      "wrongChannel": 15,
      "themization": 1
    }
  },
  "categories": {
    "deprecatedComponents": {
      "count": 0,
      "items": []
    },
    "deprecatedStyles": {
      "count": 0,
      "items": []
    },
    "customStyles": {
      "count": 13,
      "items": [
        {
          "node": {
            "id": "58613:29289",
            "name": "[M] WidjetAdvice",
            "type": "COMPONENT_SET",
            "pageName": "Виджет \"Совет\"",
            "path": "[M] WidjetAdvice",
            "visible": true
          },
          "style": {
            "type": "raw-value",
            "name": "Raw stroke",
            "key": null,
            "id": null,
            "library": null,
            "sourceFile": null
          },
          "usage": "stroke"
        },
        {
          "node": {
            "id": "58613:27844",
            "name": "Ellipse 5",
            "type": "ELLIPSE",
            "pageName": "Виджет \"Совет\"",
            "path": "[M] WidjetAdvice / Slide=Спот / Content / top spotlight / Ellipse 5",
            "visible": true
          },
          "style": {
            "type": "raw-value",
            "name": "Слой (Layer blur)",
            "key": null,
            "id": null,
            "library": null,
            "sourceFile": null
          },
          "usage": "effect:Слой (Layer blur)"
        },
        {
          "node": {
            "id": "58613:27845",
            "name": "Ellipse 4",
            "type": "ELLIPSE",
            "pageName": "Виджет \"Совет\"",
            "path": "[M] WidjetAdvice / Slide=Спот / Content / top spotlight / Ellipse 4",
            "visible": true
          },
          "style": {
            "type": "raw-value",
            "name": "Слой (Layer blur)",
            "key": null,
            "id": null,
            "library": null,
            "sourceFile": null
          },
          "usage": "effect:Слой (Layer blur)"
        },
        {
          "node": {
            "id": "58613:27847",
            "name": "Ellipse 5",
            "type": "ELLIPSE",
            "pageName": "Виджет \"Совет\"",
            "path": "[M] WidjetAdvice / Slide=Спот / Content / bottom spotlight / Ellipse 5",
            "visible": true
          },
          "style": {
            "type": "raw-value",
            "name": "Слой (Layer blur)",
            "key": null,
            "id": null,
            "library": null,
            "sourceFile": null
          },
          "usage": "effect:Слой (Layer blur)"
        },
        {
          "node": {
            "id": "58613:27848",
            "name": "Ellipse 4",
            "type": "ELLIPSE",
            "pageName": "Виджет \"Совет\"",
            "path": "[M] WidjetAdvice / Slide=Спот / Content / bottom spotlight / Ellipse 4",
            "visible": true
          },
          "style": {
            "type": "raw-value",
            "name": "Слой (Layer blur)",
            "key": null,
            "id": null,
            "library": null,
            "sourceFile": null
          },
          "usage": "effect:Слой (Layer blur)"
        },
        {
          "node": {
            "id": "58613:29302",
            "name": "Ellipse 5",
            "type": "ELLIPSE",
            "pageName": "Виджет \"Совет\"",
            "path": "[M] WidjetAdvice / Slide=Опцион / Content / top spotlight / Ellipse 5",
            "visible": true
          },
          "style": {
            "type": "raw-value",
            "name": "Слой (Layer blur)",
            "key": null,
            "id": null,
            "library": null,
            "sourceFile": null
          },
          "usage": "effect:Слой (Layer blur)"
        },
        {
          "node": {
            "id": "58613:29303",
            "name": "Ellipse 4",
            "type": "ELLIPSE",
            "pageName": "Виджет \"Совет\"",
            "path": "[M] WidjetAdvice / Slide=Опцион / Content / top spotlight / Ellipse 4",
            "visible": true
          },
          "style": {
            "type": "raw-value",
            "name": "Слой (Layer blur)",
            "key": null,
            "id": null,
            "library": null,
            "sourceFile": null
          },
          "usage": "effect:Слой (Layer blur)"
        },
        {
          "node": {
            "id": "58613:29305",
            "name": "Ellipse 5",
            "type": "ELLIPSE",
            "pageName": "Виджет \"Совет\"",
            "path": "[M] WidjetAdvice / Slide=Опцион / Content / bottom spotlight / Ellipse 5",
            "visible": true
          },
          "style": {
            "type": "raw-value",
            "name": "Слой (Layer blur)",
            "key": null,
            "id": null,
            "library": null,
            "sourceFile": null
          },
          "usage": "effect:Слой (Layer blur)"
        },
        {
          "node": {
            "id": "58613:29306",
            "name": "Ellipse 4",
            "type": "ELLIPSE",
            "pageName": "Виджет \"Совет\"",
            "path": "[M] WidjetAdvice / Slide=Опцион / Content / bottom spotlight / Ellipse 4",
            "visible": true
          },
          "style": {
            "type": "raw-value",
            "name": "Слой (Layer blur)",
            "key": null,
            "id": null,
            "library": null,
            "sourceFile": null
          },
          "usage": "effect:Слой (Layer blur)"
        },
        {
          "node": {
            "id": "58613:29347",
            "name": "Ellipse 5",
            "type": "ELLIPSE",
            "pageName": "Виджет \"Совет\"",
            "path": "[M] WidjetAdvice / Slide=Форвард / Content / top spotlight / Ellipse 5",
            "visible": true
          },
          "style": {
            "type": "raw-value",
            "name": "Слой (Layer blur)",
            "key": null,
            "id": null,
            "library": null,
            "sourceFile": null
          },
          "usage": "effect:Слой (Layer blur)"
        },
        {
          "node": {
            "id": "58613:29348",
            "name": "Ellipse 4",
            "type": "ELLIPSE",
            "pageName": "Виджет \"Совет\"",
            "path": "[M] WidjetAdvice / Slide=Форвард / Content / top spotlight / Ellipse 4",
            "visible": true
          },
          "style": {
            "type": "raw-value",
            "name": "Слой (Layer blur)",
            "key": null,
            "id": null,
            "library": null,
            "sourceFile": null
          },
          "usage": "effect:Слой (Layer blur)"
        },
        {
          "node": {
            "id": "58613:29350",
            "name": "Ellipse 5",
            "type": "ELLIPSE",
            "pageName": "Виджет \"Совет\"",
            "path": "[M] WidjetAdvice / Slide=Форвард / Content / bottom spotlight / Ellipse 5",
            "visible": true
          },
          "style": {
            "type": "raw-value",
            "name": "Слой (Layer blur)",
            "key": null,
            "id": null,
            "library": null,
            "sourceFile": null
          },
          "usage": "effect:Слой (Layer blur)"
        },
        {
          "node": {
            "id": "58613:29351",
            "name": "Ellipse 4",
            "type": "ELLIPSE",
            "pageName": "Виджет \"Совет\"",
            "path": "[M] WidjetAdvice / Slide=Форвард / Content / bottom spotlight / Ellipse 4",
            "visible": true
          },
          "style": {
            "type": "raw-value",
            "name": "Слой (Layer blur)",
            "key": null,
            "id": null,
            "library": null,
            "sourceFile": null
          },
          "usage": "effect:Слой (Layer blur)"
        }
      ]
    },
    "updates": {
      "count": 0,
      "items": []
    },
    "customizations": {
      "count": 9,
      "items": [
        {
          "node": {
            "id": "58613:27835",
            "name": "bulb-flash",
            "type": "INSTANCE",
            "pageName": "Виджет \"Совет\"",
            "path": "[M] WidjetAdvice / Slide=Спот / Content / Header / bulb-flash",
            "visible": true
          },
          "component": {
            "type": "component",
            "name": "bulb-flash",
            "key": "76655670ec8350d1e2e61e664b932742d90a358f",
            "id": null,
            "library": "Icons",
            "sourceFile": "icons/Icons -- glyph-26.json"
          },
          "variant": {
            "type": "component-variant",
            "name": "Size=20, Style=Line, Color=False",
            "key": "76655670ec8350d1e2e61e664b932742d90a358f",
            "id": null,
            "library": "Icons",
            "sourceFile": "icons/Icons -- glyph-26.json"
          },
          "comparisonIssues": [],
          "changes": [
            {
              "node": {
                "id": "I58613:27835;148564:18706",
                "name": "icon",
                "type": null,
                "pageName": "Виджет \"Совет\"",
                "path": "Size=20, Style=Line, Color=False / icon",
                "visible": true
              },
              "kind": "paint",
              "property": "fill",
              "message": "заливка: #9032EE → text/info",
              "reference": {
                "value": "#9032EE",
                "resource": null
              },
              "actual": {
                "value": "text/info",
                "resource": {
                  "type": "token",
                  "name": "text/info",
                  "key": "373a7154059297e96c397d0055152b95685c34d5",
                  "id": "VariableID:373a7154059297e96c397d0055152b95685c34d5/3541:192",
                  "library": "Interface Dynamic",
                  "sourceFile": "001 :: Interface Dynamic Colors"
                }
              },
              "signature": "component:76655670ec8350d1e2e61e664b932742d90a358f:paint:fill:#9032EE->373a7154059297e96c397d0055152b95685c34d5",
              "context": {
                "actualComponentKey": null,
                "referenceComponentKey": null,
                "referenceOrigin": "host",
                "nestedOwnerComponentKey": null,
                "nestedOwnerPath": null,
                "nestedOwnerRelativePath": null
              },
              "componentRules": [],
              "assessment": {
                "verdict": "unknown",
                "source": "standalone-reference",
                "reasonCode": "no-contextual-expectation",
                "ruleId": null,
                "message": "Контекстное правило не найдено",
                "remediation": null
              }
            }
          ]
        },
        {
          "node": {
            "id": "58613:27851",
            "name": "IconWrapper",
            "type": "INSTANCE",
            "pageName": "Виджет \"Совет\"",
            "path": "[M] WidjetAdvice / Slide=Спот / Navigation / IconWrapper",
            "visible": true
          },
          "component": {
            "type": "component",
            "name": "IconWrapper",
            "key": "110a63b51828ebe20357a4c77731cb54a7b6f0c7",
            "id": null,
            "library": "Icons",
            "sourceFile": "icons/Icons -- helper.json"
          },
          "variant": {
            "type": "component-variant",
            "name": "Size=m | 24px",
            "key": "110a63b51828ebe20357a4c77731cb54a7b6f0c7",
            "id": null,
            "library": "Icons",
            "sourceFile": "icons/Icons -- helper.json"
          },
          "comparisonIssues": [],
          "changes": [
            {
              "node": {
                "id": "I58613:27851;48263:5546",
                "name": "PaintMe",
                "type": null,
                "pageName": "Виджет \"Совет\"",
                "path": "Size=m | 24px / Wrapper / PaintMe",
                "visible": true
              },
              "kind": "paint",
              "property": "fill",
              "message": "заливка: #CF70FF → neutral/500",
              "reference": {
                "value": "#CF70FF",
                "resource": null
              },
              "actual": {
                "value": "neutral/500",
                "resource": {
                  "type": "token",
                  "name": "neutral/500",
                  "key": "ab7b3e0d9a0b4c6f0688fd7a543bb91cf30c9295",
                  "id": "VariableID:ab7b3e0d9a0b4c6f0688fd7a543bb91cf30c9295/3541:151",
                  "library": "Interface Dynamic",
                  "sourceFile": "001 :: Interface Dynamic Colors"
                }
              },
              "signature": "component:110a63b51828ebe20357a4c77731cb54a7b6f0c7:paint:fill:#CF70FF->ab7b3e0d9a0b4c6f0688fd7a543bb91cf30c9295",
              "context": {
                "actualComponentKey": null,
                "referenceComponentKey": null,
                "referenceOrigin": "host",
                "nestedOwnerComponentKey": null,
                "nestedOwnerPath": null,
                "nestedOwnerRelativePath": null
              },
              "componentRules": [],
              "assessment": {
                "verdict": "unknown",
                "source": "standalone-reference",
                "reasonCode": "no-contextual-expectation",
                "ruleId": null,
                "message": "Контекстное правило не найдено",
                "remediation": null
              }
            }
          ]
        },
        {
          "node": {
            "id": "58613:27858",
            "name": "IconWrapper",
            "type": "INSTANCE",
            "pageName": "Виджет \"Совет\"",
            "path": "[M] WidjetAdvice / Slide=Спот / Navigation / IconWrapper",
            "visible": true
          },
          "component": {
            "type": "component",
            "name": "IconWrapper",
            "key": "110a63b51828ebe20357a4c77731cb54a7b6f0c7",
            "id": null,
            "library": "Icons",
            "sourceFile": "icons/Icons -- helper.json"
          },
          "variant": {
            "type": "component-variant",
            "name": "Size=m | 24px",
            "key": "110a63b51828ebe20357a4c77731cb54a7b6f0c7",
            "id": null,
            "library": "Icons",
            "sourceFile": "icons/Icons -- helper.json"
          },
          "comparisonIssues": [],
          "changes": [
            {
              "node": {
                "id": "I58613:27858;48263:5546",
                "name": "PaintMe",
                "type": null,
                "pageName": "Виджет \"Совет\"",
                "path": "Size=m | 24px / Wrapper / PaintMe",
                "visible": true
              },
              "kind": "paint",
              "property": "fill",
              "message": "заливка: #CF70FF → neutral/1300",
              "reference": {
                "value": "#CF70FF",
                "resource": null
              },
              "actual": {
                "value": "neutral/1300",
                "resource": {
                  "type": "token",
                  "name": "neutral/1300",
                  "key": "d8fdd2d33bde75b054a497055e53d61a7553c3e3",
                  "id": "VariableID:d8fdd2d33bde75b054a497055e53d61a7553c3e3/3541:169",
                  "library": "Interface Dynamic",
                  "sourceFile": "001 :: Interface Dynamic Colors"
                }
              },
              "signature": "component:110a63b51828ebe20357a4c77731cb54a7b6f0c7:paint:fill:#CF70FF->d8fdd2d33bde75b054a497055e53d61a7553c3e3",
              "context": {
                "actualComponentKey": null,
                "referenceComponentKey": null,
                "referenceOrigin": "host",
                "nestedOwnerComponentKey": null,
                "nestedOwnerPath": null,
                "nestedOwnerRelativePath": null
              },
              "componentRules": [],
              "assessment": {
                "verdict": "unknown",
                "source": "standalone-reference",
                "reasonCode": "no-contextual-expectation",
                "ruleId": null,
                "message": "Контекстное правило не найдено",
                "remediation": null
              }
            }
          ]
        },
        {
          "node": {
            "id": "58613:29293",
            "name": "bulb-flash",
            "type": "INSTANCE",
            "pageName": "Виджет \"Совет\"",
            "path": "[M] WidjetAdvice / Slide=Опцион / Content / Header / bulb-flash",
            "visible": true
          },
          "component": {
            "type": "component",
            "name": "bulb-flash",
            "key": "76655670ec8350d1e2e61e664b932742d90a358f",
            "id": null,
            "library": "Icons",
            "sourceFile": "icons/Icons -- glyph-26.json"
          },
          "variant": {
            "type": "component-variant",
            "name": "Size=20, Style=Line, Color=False",
            "key": "76655670ec8350d1e2e61e664b932742d90a358f",
            "id": null,
            "library": "Icons",
            "sourceFile": "icons/Icons -- glyph-26.json"
          },
          "comparisonIssues": [],
          "changes": [
            {
              "node": {
                "id": "I58613:29293;148564:18706",
                "name": "icon",
                "type": null,
                "pageName": "Виджет \"Совет\"",
                "path": "Size=20, Style=Line, Color=False / icon",
                "visible": true
              },
              "kind": "paint",
              "property": "fill",
              "message": "заливка: #9032EE → text/info",
              "reference": {
                "value": "#9032EE",
                "resource": null
              },
              "actual": {
                "value": "text/info",
                "resource": {
                  "type": "token",
                  "name": "text/info",
                  "key": "373a7154059297e96c397d0055152b95685c34d5",
                  "id": "VariableID:373a7154059297e96c397d0055152b95685c34d5/3541:192",
                  "library": "Interface Dynamic",
                  "sourceFile": "001 :: Interface Dynamic Colors"
                }
              },
              "signature": "component:76655670ec8350d1e2e61e664b932742d90a358f:paint:fill:#9032EE->373a7154059297e96c397d0055152b95685c34d5",
              "context": {
                "actualComponentKey": null,
                "referenceComponentKey": null,
                "referenceOrigin": "host",
                "nestedOwnerComponentKey": null,
                "nestedOwnerPath": null,
                "nestedOwnerRelativePath": null
              },
              "componentRules": [],
              "assessment": {
                "verdict": "unknown",
                "source": "standalone-reference",
                "reasonCode": "no-contextual-expectation",
                "ruleId": null,
                "message": "Контекстное правило не найдено",
                "remediation": null
              }
            }
          ]
        },
        {
          "node": {
            "id": "58613:29309",
            "name": "IconWrapper",
            "type": "INSTANCE",
            "pageName": "Виджет \"Совет\"",
            "path": "[M] WidjetAdvice / Slide=Опцион / Navigation / IconWrapper",
            "visible": true
          },
          "component": {
            "type": "component",
            "name": "IconWrapper",
            "key": "110a63b51828ebe20357a4c77731cb54a7b6f0c7",
            "id": null,
            "library": "Icons",
            "sourceFile": "icons/Icons -- helper.json"
          },
          "variant": {
            "type": "component-variant",
            "name": "Size=m | 24px",
            "key": "110a63b51828ebe20357a4c77731cb54a7b6f0c7",
            "id": null,
            "library": "Icons",
            "sourceFile": "icons/Icons -- helper.json"
          },
          "comparisonIssues": [],
          "changes": [
            {
              "node": {
                "id": "I58613:29309;48263:5546",
                "name": "PaintMe",
                "type": null,
                "pageName": "Виджет \"Совет\"",
                "path": "Size=m | 24px / Wrapper / PaintMe",
                "visible": true
              },
              "kind": "paint",
              "property": "fill",
              "message": "заливка: #CF70FF → neutral/1300",
              "reference": {
                "value": "#CF70FF",
                "resource": null
              },
              "actual": {
                "value": "neutral/1300",
                "resource": {
                  "type": "token",
                  "name": "neutral/1300",
                  "key": "d8fdd2d33bde75b054a497055e53d61a7553c3e3",
                  "id": "VariableID:d8fdd2d33bde75b054a497055e53d61a7553c3e3/3541:169",
                  "library": "Interface Dynamic",
                  "sourceFile": "001 :: Interface Dynamic Colors"
                }
              },
              "signature": "component:110a63b51828ebe20357a4c77731cb54a7b6f0c7:paint:fill:#CF70FF->d8fdd2d33bde75b054a497055e53d61a7553c3e3",
              "context": {
                "actualComponentKey": null,
                "referenceComponentKey": null,
                "referenceOrigin": "host",
                "nestedOwnerComponentKey": null,
                "nestedOwnerPath": null,
                "nestedOwnerRelativePath": null
              },
              "componentRules": [],
              "assessment": {
                "verdict": "unknown",
                "source": "standalone-reference",
                "reasonCode": "no-contextual-expectation",
                "ruleId": null,
                "message": "Контекстное правило не найдено",
                "remediation": null
              }
            }
          ]
        },
        {
          "node": {
            "id": "58613:29316",
            "name": "IconWrapper",
            "type": "INSTANCE",
            "pageName": "Виджет \"Совет\"",
            "path": "[M] WidjetAdvice / Slide=Опцион / Navigation / IconWrapper",
            "visible": true
          },
          "component": {
            "type": "component",
            "name": "IconWrapper",
            "key": "110a63b51828ebe20357a4c77731cb54a7b6f0c7",
            "id": null,
            "library": "Icons",
            "sourceFile": "icons/Icons -- helper.json"
          },
          "variant": {
            "type": "component-variant",
            "name": "Size=m | 24px",
            "key": "110a63b51828ebe20357a4c77731cb54a7b6f0c7",
            "id": null,
            "library": "Icons",
            "sourceFile": "icons/Icons -- helper.json"
          },
          "comparisonIssues": [],
          "changes": [
            {
              "node": {
                "id": "I58613:29316;48263:5546",
                "name": "PaintMe",
                "type": null,
                "pageName": "Виджет \"Совет\"",
                "path": "Size=m | 24px / Wrapper / PaintMe",
                "visible": true
              },
              "kind": "paint",
              "property": "fill",
              "message": "заливка: #CF70FF → neutral/1300",
              "reference": {
                "value": "#CF70FF",
                "resource": null
              },
              "actual": {
                "value": "neutral/1300",
                "resource": {
                  "type": "token",
                  "name": "neutral/1300",
                  "key": "d8fdd2d33bde75b054a497055e53d61a7553c3e3",
                  "id": "VariableID:d8fdd2d33bde75b054a497055e53d61a7553c3e3/3541:169",
                  "library": "Interface Dynamic",
                  "sourceFile": "001 :: Interface Dynamic Colors"
                }
              },
              "signature": "component:110a63b51828ebe20357a4c77731cb54a7b6f0c7:paint:fill:#CF70FF->d8fdd2d33bde75b054a497055e53d61a7553c3e3",
              "context": {
                "actualComponentKey": null,
                "referenceComponentKey": null,
                "referenceOrigin": "host",
                "nestedOwnerComponentKey": null,
                "nestedOwnerPath": null,
                "nestedOwnerRelativePath": null
              },
              "componentRules": [],
              "assessment": {
                "verdict": "unknown",
                "source": "standalone-reference",
                "reasonCode": "no-contextual-expectation",
                "ruleId": null,
                "message": "Контекстное правило не найдено",
                "remediation": null
              }
            }
          ]
        },
        {
          "node": {
            "id": "58613:29338",
            "name": "bulb-flash",
            "type": "INSTANCE",
            "pageName": "Виджет \"Совет\"",
            "path": "[M] WidjetAdvice / Slide=Форвард / Content / Header / bulb-flash",
            "visible": true
          },
          "component": {
            "type": "component",
            "name": "bulb-flash",
            "key": "76655670ec8350d1e2e61e664b932742d90a358f",
            "id": null,
            "library": "Icons",
            "sourceFile": "icons/Icons -- glyph-26.json"
          },
          "variant": {
            "type": "component-variant",
            "name": "Size=20, Style=Line, Color=False",
            "key": "76655670ec8350d1e2e61e664b932742d90a358f",
            "id": null,
            "library": "Icons",
            "sourceFile": "icons/Icons -- glyph-26.json"
          },
          "comparisonIssues": [],
          "changes": [
            {
              "node": {
                "id": "I58613:29338;148564:18706",
                "name": "icon",
                "type": null,
                "pageName": "Виджет \"Совет\"",
                "path": "Size=20, Style=Line, Color=False / icon",
                "visible": true
              },
              "kind": "paint",
              "property": "fill",
              "message": "заливка: #9032EE → text/info",
              "reference": {
                "value": "#9032EE",
                "resource": null
              },
              "actual": {
                "value": "text/info",
                "resource": {
                  "type": "token",
                  "name": "text/info",
                  "key": "373a7154059297e96c397d0055152b95685c34d5",
                  "id": "VariableID:373a7154059297e96c397d0055152b95685c34d5/3541:192",
                  "library": "Interface Dynamic",
                  "sourceFile": "001 :: Interface Dynamic Colors"
                }
              },
              "signature": "component:76655670ec8350d1e2e61e664b932742d90a358f:paint:fill:#9032EE->373a7154059297e96c397d0055152b95685c34d5",
              "context": {
                "actualComponentKey": null,
                "referenceComponentKey": null,
                "referenceOrigin": "host",
                "nestedOwnerComponentKey": null,
                "nestedOwnerPath": null,
                "nestedOwnerRelativePath": null
              },
              "componentRules": [],
              "assessment": {
                "verdict": "unknown",
                "source": "standalone-reference",
                "reasonCode": "no-contextual-expectation",
                "ruleId": null,
                "message": "Контекстное правило не найдено",
                "remediation": null
              }
            }
          ]
        },
        {
          "node": {
            "id": "58613:29354",
            "name": "IconWrapper",
            "type": "INSTANCE",
            "pageName": "Виджет \"Совет\"",
            "path": "[M] WidjetAdvice / Slide=Форвард / Navigation / IconWrapper",
            "visible": true
          },
          "component": {
            "type": "component",
            "name": "IconWrapper",
            "key": "110a63b51828ebe20357a4c77731cb54a7b6f0c7",
            "id": null,
            "library": "Icons",
            "sourceFile": "icons/Icons -- helper.json"
          },
          "variant": {
            "type": "component-variant",
            "name": "Size=m | 24px",
            "key": "110a63b51828ebe20357a4c77731cb54a7b6f0c7",
            "id": null,
            "library": "Icons",
            "sourceFile": "icons/Icons -- helper.json"
          },
          "comparisonIssues": [],
          "changes": [
            {
              "node": {
                "id": "I58613:29354;48263:5546",
                "name": "PaintMe",
                "type": null,
                "pageName": "Виджет \"Совет\"",
                "path": "Size=m | 24px / Wrapper / PaintMe",
                "visible": true
              },
              "kind": "paint",
              "property": "fill",
              "message": "заливка: #CF70FF → neutral/1300",
              "reference": {
                "value": "#CF70FF",
                "resource": null
              },
              "actual": {
                "value": "neutral/1300",
                "resource": {
                  "type": "token",
                  "name": "neutral/1300",
                  "key": "d8fdd2d33bde75b054a497055e53d61a7553c3e3",
                  "id": "VariableID:d8fdd2d33bde75b054a497055e53d61a7553c3e3/3541:169",
                  "library": "Interface Dynamic",
                  "sourceFile": "001 :: Interface Dynamic Colors"
                }
              },
              "signature": "component:110a63b51828ebe20357a4c77731cb54a7b6f0c7:paint:fill:#CF70FF->d8fdd2d33bde75b054a497055e53d61a7553c3e3",
              "context": {
                "actualComponentKey": null,
                "referenceComponentKey": null,
                "referenceOrigin": "host",
                "nestedOwnerComponentKey": null,
                "nestedOwnerPath": null,
                "nestedOwnerRelativePath": null
              },
              "componentRules": [],
              "assessment": {
                "verdict": "unknown",
                "source": "standalone-reference",
                "reasonCode": "no-contextual-expectation",
                "ruleId": null,
                "message": "Контекстное правило не найдено",
                "remediation": null
              }
            }
          ]
        },
        {
          "node": {
            "id": "58613:29361",
            "name": "IconWrapper",
            "type": "INSTANCE",
            "pageName": "Виджет \"Совет\"",
            "path": "[M] WidjetAdvice / Slide=Форвард / Navigation / IconWrapper",
            "visible": true
          },
          "component": {
            "type": "component",
            "name": "IconWrapper",
            "key": "110a63b51828ebe20357a4c77731cb54a7b6f0c7",
            "id": null,
            "library": "Icons",
            "sourceFile": "icons/Icons -- helper.json"
          },
          "variant": {
            "type": "component-variant",
            "name": "Size=m | 24px",
            "key": "110a63b51828ebe20357a4c77731cb54a7b6f0c7",
            "id": null,
            "library": "Icons",
            "sourceFile": "icons/Icons -- helper.json"
          },
          "comparisonIssues": [],
          "changes": [
            {
              "node": {
                "id": "I58613:29361;48263:5546",
                "name": "PaintMe",
                "type": null,
                "pageName": "Виджет \"Совет\"",
                "path": "Size=m | 24px / Wrapper / PaintMe",
                "visible": true
              },
              "kind": "paint",
              "property": "fill",
              "message": "заливка: #CF70FF → neutral/500",
              "reference": {
                "value": "#CF70FF",
                "resource": null
              },
              "actual": {
                "value": "neutral/500",
                "resource": {
                  "type": "token",
                  "name": "neutral/500",
                  "key": "ab7b3e0d9a0b4c6f0688fd7a543bb91cf30c9295",
                  "id": "VariableID:ab7b3e0d9a0b4c6f0688fd7a543bb91cf30c9295/3541:151",
                  "library": "Interface Dynamic",
                  "sourceFile": "001 :: Interface Dynamic Colors"
                }
              },
              "signature": "component:110a63b51828ebe20357a4c77731cb54a7b6f0c7:paint:fill:#CF70FF->ab7b3e0d9a0b4c6f0688fd7a543bb91cf30c9295",
              "context": {
                "actualComponentKey": null,
                "referenceComponentKey": null,
                "referenceOrigin": "host",
                "nestedOwnerComponentKey": null,
                "nestedOwnerPath": null,
                "nestedOwnerRelativePath": null
              },
              "componentRules": [],
              "assessment": {
                "verdict": "unknown",
                "source": "standalone-reference",
                "reasonCode": "no-contextual-expectation",
                "ruleId": null,
                "message": "Контекстное правило не найдено",
                "remediation": null
              }
            }
          ]
        }
      ]
    },
    "localComponents": {
      "count": 3,
      "items": [
        {
          "node": {
            "id": "58613:29288",
            "name": "Slide=Спот",
            "type": "COMPONENT",
            "pageName": "Виджет \"Совет\"",
            "path": "[M] WidjetAdvice / Slide=Спот",
            "visible": true
          },
          "component": {
            "type": "component",
            "name": "Slide=Спот",
            "key": "922c82990318712192330b9c0cda9b9fa08457fb",
            "id": null,
            "library": null,
            "sourceFile": null
          },
          "variant": null,
          "comparisonIssues": []
        },
        {
          "node": {
            "id": "58613:29290",
            "name": "Slide=Опцион",
            "type": "COMPONENT",
            "pageName": "Виджет \"Совет\"",
            "path": "[M] WidjetAdvice / Slide=Опцион",
            "visible": true
          },
          "component": {
            "type": "component",
            "name": "Slide=Опцион",
            "key": "15bdba576af94a04adb8633b6533c20c69942fee",
            "id": null,
            "library": null,
            "sourceFile": null
          },
          "variant": null,
          "comparisonIssues": []
        },
        {
          "node": {
            "id": "58613:29335",
            "name": "Slide=Форвард",
            "type": "COMPONENT",
            "pageName": "Виджет \"Совет\"",
            "path": "[M] WidjetAdvice / Slide=Форвард",
            "visible": true
          },
          "component": {
            "type": "component",
            "name": "Slide=Форвард",
            "key": "de039715df705064751ee5b6dee0d4e67d8f36f9",
            "id": null,
            "library": null,
            "sourceFile": null
          },
          "variant": null,
          "comparisonIssues": []
        }
      ]
    },
    "detachedComponents": {
      "count": 0,
      "items": []
    },
    "presets": {
      "count": 0,
      "items": []
    },
    "technicalComponents": {
      "count": 0,
      "items": []
    },
    "currentComponents": {
      "count": 15,
      "items": [
        {
          "node": {
            "id": "58613:27835",
            "name": "bulb-flash",
            "type": "INSTANCE",
            "pageName": "Виджет \"Совет\"",
            "path": "[M] WidjetAdvice / Slide=Спот / Content / Header / bulb-flash",
            "visible": true
          },
          "component": {
            "type": "component",
            "name": "bulb-flash",
            "key": "76655670ec8350d1e2e61e664b932742d90a358f",
            "id": null,
            "library": "Icons",
            "sourceFile": "icons/Icons -- glyph-26.json"
          },
          "variant": {
            "type": "component-variant",
            "name": "Size=20, Style=Line, Color=False",
            "key": "76655670ec8350d1e2e61e664b932742d90a358f",
            "id": null,
            "library": "Icons",
            "sourceFile": "icons/Icons -- glyph-26.json"
          },
          "comparisonIssues": []
        },
        {
          "node": {
            "id": "58613:27851",
            "name": "IconWrapper",
            "type": "INSTANCE",
            "pageName": "Виджет \"Совет\"",
            "path": "[M] WidjetAdvice / Slide=Спот / Navigation / IconWrapper",
            "visible": true
          },
          "component": {
            "type": "component",
            "name": "IconWrapper",
            "key": "110a63b51828ebe20357a4c77731cb54a7b6f0c7",
            "id": null,
            "library": "Icons",
            "sourceFile": "icons/Icons -- helper.json"
          },
          "variant": {
            "type": "component-variant",
            "name": "Size=m | 24px",
            "key": "110a63b51828ebe20357a4c77731cb54a7b6f0c7",
            "id": null,
            "library": "Icons",
            "sourceFile": "icons/Icons -- helper.json"
          },
          "comparisonIssues": []
        },
        {
          "node": {
            "id": "I58613:27851;48263:5548",
            "name": "chevron-left",
            "type": "INSTANCE",
            "pageName": "Виджет \"Совет\"",
            "path": "[M] WidjetAdvice / Slide=Спот / Navigation / IconWrapper / Wrapper / PaintMe / chevron-left",
            "visible": true
          },
          "component": {
            "type": "component",
            "name": "chevron-left",
            "key": "9fb11d31e59bc32ac07f1bfb44f2ce2bd48e5777",
            "id": null,
            "library": "Icons",
            "sourceFile": "icons/Icons -- glyph-26.json"
          },
          "variant": {
            "type": "component-variant",
            "name": "Size=24, Style=Line, Color=False",
            "key": "9fb11d31e59bc32ac07f1bfb44f2ce2bd48e5777",
            "id": null,
            "library": "Icons",
            "sourceFile": "icons/Icons -- glyph-26.json"
          },
          "comparisonIssues": []
        },
        {
          "node": {
            "id": "58613:27858",
            "name": "IconWrapper",
            "type": "INSTANCE",
            "pageName": "Виджет \"Совет\"",
            "path": "[M] WidjetAdvice / Slide=Спот / Navigation / IconWrapper",
            "visible": true
          },
          "component": {
            "type": "component",
            "name": "IconWrapper",
            "key": "110a63b51828ebe20357a4c77731cb54a7b6f0c7",
            "id": null,
            "library": "Icons",
            "sourceFile": "icons/Icons -- helper.json"
          },
          "variant": {
            "type": "component-variant",
            "name": "Size=m | 24px",
            "key": "110a63b51828ebe20357a4c77731cb54a7b6f0c7",
            "id": null,
            "library": "Icons",
            "sourceFile": "icons/Icons -- helper.json"
          },
          "comparisonIssues": []
        },
        {
          "node": {
            "id": "I58613:27858;48263:5548",
            "name": "chevron-right",
            "type": "INSTANCE",
            "pageName": "Виджет \"Совет\"",
            "path": "[M] WidjetAdvice / Slide=Спот / Navigation / IconWrapper / Wrapper / PaintMe / chevron-right",
            "visible": true
          },
          "component": {
            "type": "component",
            "name": "chevron-right",
            "key": "92fec832588949a9108b7d590b9d2fa837808328",
            "id": null,
            "library": "Icons",
            "sourceFile": "icons/Icons -- glyph-26.json"
          },
          "variant": {
            "type": "component-variant",
            "name": "Size=24, Style=Line, Color=False",
            "key": "92fec832588949a9108b7d590b9d2fa837808328",
            "id": null,
            "library": "Icons",
            "sourceFile": "icons/Icons -- glyph-26.json"
          },
          "comparisonIssues": []
        },
        {
          "node": {
            "id": "58613:29293",
            "name": "bulb-flash",
            "type": "INSTANCE",
            "pageName": "Виджет \"Совет\"",
            "path": "[M] WidjetAdvice / Slide=Опцион / Content / Header / bulb-flash",
            "visible": true
          },
          "component": {
            "type": "component",
            "name": "bulb-flash",
            "key": "76655670ec8350d1e2e61e664b932742d90a358f",
            "id": null,
            "library": "Icons",
            "sourceFile": "icons/Icons -- glyph-26.json"
          },
          "variant": {
            "type": "component-variant",
            "name": "Size=20, Style=Line, Color=False",
            "key": "76655670ec8350d1e2e61e664b932742d90a358f",
            "id": null,
            "library": "Icons",
            "sourceFile": "icons/Icons -- glyph-26.json"
          },
          "comparisonIssues": []
        },
        {
          "node": {
            "id": "58613:29309",
            "name": "IconWrapper",
            "type": "INSTANCE",
            "pageName": "Виджет \"Совет\"",
            "path": "[M] WidjetAdvice / Slide=Опцион / Navigation / IconWrapper",
            "visible": true
          },
          "component": {
            "type": "component",
            "name": "IconWrapper",
            "key": "110a63b51828ebe20357a4c77731cb54a7b6f0c7",
            "id": null,
            "library": "Icons",
            "sourceFile": "icons/Icons -- helper.json"
          },
          "variant": {
            "type": "component-variant",
            "name": "Size=m | 24px",
            "key": "110a63b51828ebe20357a4c77731cb54a7b6f0c7",
            "id": null,
            "library": "Icons",
            "sourceFile": "icons/Icons -- helper.json"
          },
          "comparisonIssues": []
        },
        {
          "node": {
            "id": "I58613:29309;48263:5548",
            "name": "chevron-left",
            "type": "INSTANCE",
            "pageName": "Виджет \"Совет\"",
            "path": "[M] WidjetAdvice / Slide=Опцион / Navigation / IconWrapper / Wrapper / PaintMe / chevron-left",
            "visible": true
          },
          "component": {
            "type": "component",
            "name": "chevron-left",
            "key": "9fb11d31e59bc32ac07f1bfb44f2ce2bd48e5777",
            "id": null,
            "library": "Icons",
            "sourceFile": "icons/Icons -- glyph-26.json"
          },
          "variant": {
            "type": "component-variant",
            "name": "Size=24, Style=Line, Color=False",
            "key": "9fb11d31e59bc32ac07f1bfb44f2ce2bd48e5777",
            "id": null,
            "library": "Icons",
            "sourceFile": "icons/Icons -- glyph-26.json"
          },
          "comparisonIssues": []
        },
        {
          "node": {
            "id": "58613:29316",
            "name": "IconWrapper",
            "type": "INSTANCE",
            "pageName": "Виджет \"Совет\"",
            "path": "[M] WidjetAdvice / Slide=Опцион / Navigation / IconWrapper",
            "visible": true
          },
          "component": {
            "type": "component",
            "name": "IconWrapper",
            "key": "110a63b51828ebe20357a4c77731cb54a7b6f0c7",
            "id": null,
            "library": "Icons",
            "sourceFile": "icons/Icons -- helper.json"
          },
          "variant": {
            "type": "component-variant",
            "name": "Size=m | 24px",
            "key": "110a63b51828ebe20357a4c77731cb54a7b6f0c7",
            "id": null,
            "library": "Icons",
            "sourceFile": "icons/Icons -- helper.json"
          },
          "comparisonIssues": []
        },
        {
          "node": {
            "id": "I58613:29316;48263:5548",
            "name": "chevron-right",
            "type": "INSTANCE",
            "pageName": "Виджет \"Совет\"",
            "path": "[M] WidjetAdvice / Slide=Опцион / Navigation / IconWrapper / Wrapper / PaintMe / chevron-right",
            "visible": true
          },
          "component": {
            "type": "component",
            "name": "chevron-right",
            "key": "92fec832588949a9108b7d590b9d2fa837808328",
            "id": null,
            "library": "Icons",
            "sourceFile": "icons/Icons -- glyph-26.json"
          },
          "variant": {
            "type": "component-variant",
            "name": "Size=24, Style=Line, Color=False",
            "key": "92fec832588949a9108b7d590b9d2fa837808328",
            "id": null,
            "library": "Icons",
            "sourceFile": "icons/Icons -- glyph-26.json"
          },
          "comparisonIssues": []
        },
        {
          "node": {
            "id": "58613:29338",
            "name": "bulb-flash",
            "type": "INSTANCE",
            "pageName": "Виджет \"Совет\"",
            "path": "[M] WidjetAdvice / Slide=Форвард / Content / Header / bulb-flash",
            "visible": true
          },
          "component": {
            "type": "component",
            "name": "bulb-flash",
            "key": "76655670ec8350d1e2e61e664b932742d90a358f",
            "id": null,
            "library": "Icons",
            "sourceFile": "icons/Icons -- glyph-26.json"
          },
          "variant": {
            "type": "component-variant",
            "name": "Size=20, Style=Line, Color=False",
            "key": "76655670ec8350d1e2e61e664b932742d90a358f",
            "id": null,
            "library": "Icons",
            "sourceFile": "icons/Icons -- glyph-26.json"
          },
          "comparisonIssues": []
        },
        {
          "node": {
            "id": "58613:29354",
            "name": "IconWrapper",
            "type": "INSTANCE",
            "pageName": "Виджет \"Совет\"",
            "path": "[M] WidjetAdvice / Slide=Форвард / Navigation / IconWrapper",
            "visible": true
          },
          "component": {
            "type": "component",
            "name": "IconWrapper",
            "key": "110a63b51828ebe20357a4c77731cb54a7b6f0c7",
            "id": null,
            "library": "Icons",
            "sourceFile": "icons/Icons -- helper.json"
          },
          "variant": {
            "type": "component-variant",
            "name": "Size=m | 24px",
            "key": "110a63b51828ebe20357a4c77731cb54a7b6f0c7",
            "id": null,
            "library": "Icons",
            "sourceFile": "icons/Icons -- helper.json"
          },
          "comparisonIssues": []
        },
        {
          "node": {
            "id": "I58613:29354;48263:5548",
            "name": "chevron-left",
            "type": "INSTANCE",
            "pageName": "Виджет \"Совет\"",
            "path": "[M] WidjetAdvice / Slide=Форвард / Navigation / IconWrapper / Wrapper / PaintMe / chevron-left",
            "visible": true
          },
          "component": {
            "type": "component",
            "name": "chevron-left",
            "key": "9fb11d31e59bc32ac07f1bfb44f2ce2bd48e5777",
            "id": null,
            "library": "Icons",
            "sourceFile": "icons/Icons -- glyph-26.json"
          },
          "variant": {
            "type": "component-variant",
            "name": "Size=24, Style=Line, Color=False",
            "key": "9fb11d31e59bc32ac07f1bfb44f2ce2bd48e5777",
            "id": null,
            "library": "Icons",
            "sourceFile": "icons/Icons -- glyph-26.json"
          },
          "comparisonIssues": []
        },
        {
          "node": {
            "id": "58613:29361",
            "name": "IconWrapper",
            "type": "INSTANCE",
            "pageName": "Виджет \"Совет\"",
            "path": "[M] WidjetAdvice / Slide=Форвард / Navigation / IconWrapper",
            "visible": true
          },
          "component": {
            "type": "component",
            "name": "IconWrapper",
            "key": "110a63b51828ebe20357a4c77731cb54a7b6f0c7",
            "id": null,
            "library": "Icons",
            "sourceFile": "icons/Icons -- helper.json"
          },
          "variant": {
            "type": "component-variant",
            "name": "Size=m | 24px",
            "key": "110a63b51828ebe20357a4c77731cb54a7b6f0c7",
            "id": null,
            "library": "Icons",
            "sourceFile": "icons/Icons -- helper.json"
          },
          "comparisonIssues": []
        },
        {
          "node": {
            "id": "I58613:29361;48263:5548",
            "name": "chevron-right",
            "type": "INSTANCE",
            "pageName": "Виджет \"Совет\"",
            "path": "[M] WidjetAdvice / Slide=Форвард / Navigation / IconWrapper / Wrapper / PaintMe / chevron-right",
            "visible": true
          },
          "component": {
            "type": "component",
            "name": "chevron-right",
            "key": "92fec832588949a9108b7d590b9d2fa837808328",
            "id": null,
            "library": "Icons",
            "sourceFile": "icons/Icons -- glyph-26.json"
          },
          "variant": {
            "type": "component-variant",
            "name": "Size=24, Style=Line, Color=False",
            "key": "92fec832588949a9108b7d590b9d2fa837808328",
            "id": null,
            "library": "Icons",
            "sourceFile": "icons/Icons -- glyph-26.json"
          },
          "comparisonIssues": []
        }
      ]
    },
    "wrongChannel": {
      "count": 15,
      "items": [
        {
          "node": {
            "id": "58613:27842",
            "name": "[M] Button",
            "type": "INSTANCE",
            "pageName": "Виджет \"Совет\"",
            "path": "[M] WidjetAdvice / Slide=Спот / Content / Bottom / Controlls / [M] Button",
            "visible": true
          },
          "component": {
            "type": "component",
            "name": "[M] Button",
            "key": "369e0ac445a5a268b6165161f58793685b090f39",
            "id": null,
            "library": "Web _ Core",
            "sourceFile": "web/components/web-core/core/Web _ Core -- Button.json"
          },
          "variant": {
            "type": "component-variant",
            "name": "View=Secondary, Size=32, Shape=Rectangular, SingleIcon=False, DisabledState=False",
            "key": "369e0ac445a5a268b6165161f58793685b090f39",
            "id": null,
            "library": "Web _ Core",
            "sourceFile": "web/components/web-core/core/Web _ Core -- Button.json"
          },
          "comparisonIssues": [
            "Нет данных для скруглений в снапшоте для «View=Secondary, Size=32, Shape=Rectangular, SingleIcon=False, DisabledState=False / Text / Label»"
          ]
        },
        {
          "node": {
            "id": "58613:27849",
            "name": "[M] BackgroundPlate",
            "type": "INSTANCE",
            "pageName": "Виджет \"Совет\"",
            "path": "[M] WidjetAdvice / Slide=Спот / Content / [M] BackgroundPlate",
            "visible": true
          },
          "component": {
            "type": "component",
            "name": "[M] BackgroundPlate",
            "key": "e5542ae4d2f93c65ce520258e8060738c38a4976",
            "id": null,
            "library": "Web _ Corp Components",
            "sourceFile": "web/components/web-corp/Web _ Corp Components -- BackgroundPlate.json"
          },
          "variant": {
            "type": "component-variant",
            "name": "Position=Level 2 (inner)",
            "key": "e5542ae4d2f93c65ce520258e8060738c38a4976",
            "id": null,
            "library": "Web _ Corp Components",
            "sourceFile": "web/components/web-corp/Web _ Corp Components -- BackgroundPlate.json"
          },
          "comparisonIssues": []
        },
        {
          "node": {
            "id": "I58613:27849;66402:30707",
            "name": "[M] Style Level 2",
            "type": "INSTANCE",
            "pageName": "Виджет \"Совет\"",
            "path": "[M] WidjetAdvice / Slide=Спот / Content / [M] BackgroundPlate / [M] Style Level 2",
            "visible": true
          },
          "component": {
            "type": "component",
            "name": "[M] Style Level 2",
            "key": "b2dca6f62c6a8e50f1762cf47f3eeae2a35618c7",
            "id": null,
            "library": "Web _ Corp Components",
            "sourceFile": "web/components/web-corp/Web _ Corp Components -- BackgroundPlate.json"
          },
          "variant": {
            "type": "component-variant",
            "name": "BackgroundColor=base-bg-alt (gray), Type=Primary, Skeleton=False",
            "key": "b2dca6f62c6a8e50f1762cf47f3eeae2a35618c7",
            "id": null,
            "library": "Web _ Corp Components",
            "sourceFile": "web/components/web-corp/Web _ Corp Components -- BackgroundPlate.json"
          },
          "comparisonIssues": []
        },
        {
          "node": {
            "id": "58613:34018",
            "name": "[M] BackgroundPlate",
            "type": "INSTANCE",
            "pageName": "Виджет \"Совет\"",
            "path": "[M] WidjetAdvice / Slide=Спот / [M] BackgroundPlate",
            "visible": true
          },
          "component": {
            "type": "component",
            "name": "[M] BackgroundPlate",
            "key": "41e2c5c17d573baf32ae78d01b69c0a3d7ba033c",
            "id": null,
            "library": "Web _ Corp Components",
            "sourceFile": "web/components/web-corp/Web _ Corp Components -- BackgroundPlate.json"
          },
          "variant": {
            "type": "component-variant",
            "name": "Position=Level 1 (outer)",
            "key": "41e2c5c17d573baf32ae78d01b69c0a3d7ba033c",
            "id": null,
            "library": "Web _ Corp Components",
            "sourceFile": "web/components/web-corp/Web _ Corp Components -- BackgroundPlate.json"
          },
          "comparisonIssues": []
        },
        {
          "node": {
            "id": "I58613:34018;66402:30705",
            "name": "[M] Style Level 1",
            "type": "INSTANCE",
            "pageName": "Виджет \"Совет\"",
            "path": "[M] WidjetAdvice / Slide=Спот / [M] BackgroundPlate / [M] Style Level 1",
            "visible": true
          },
          "component": {
            "type": "component",
            "name": "[M] Style Level 1",
            "key": "cdc3f827449db161006abe2250f936b0ee27fafc",
            "id": null,
            "library": "Web _ Corp Components",
            "sourceFile": "web/components/web-corp/Web _ Corp Components -- BackgroundPlate.json"
          },
          "variant": {
            "type": "component-variant",
            "name": "BackgroundColor=base-bg (white), Type=Primary, Skeleton=False",
            "key": "cdc3f827449db161006abe2250f936b0ee27fafc",
            "id": null,
            "library": "Web _ Corp Components",
            "sourceFile": "web/components/web-corp/Web _ Corp Components -- BackgroundPlate.json"
          },
          "comparisonIssues": []
        },
        {
          "node": {
            "id": "58613:29300",
            "name": "[M] Button",
            "type": "INSTANCE",
            "pageName": "Виджет \"Совет\"",
            "path": "[M] WidjetAdvice / Slide=Опцион / Content / Bottom / Controlls / [M] Button",
            "visible": true
          },
          "component": {
            "type": "component",
            "name": "[M] Button",
            "key": "369e0ac445a5a268b6165161f58793685b090f39",
            "id": null,
            "library": "Web _ Core",
            "sourceFile": "web/components/web-core/core/Web _ Core -- Button.json"
          },
          "variant": {
            "type": "component-variant",
            "name": "View=Secondary, Size=32, Shape=Rectangular, SingleIcon=False, DisabledState=False",
            "key": "369e0ac445a5a268b6165161f58793685b090f39",
            "id": null,
            "library": "Web _ Core",
            "sourceFile": "web/components/web-core/core/Web _ Core -- Button.json"
          },
          "comparisonIssues": [
            "Нет данных для скруглений в снапшоте для «View=Secondary, Size=32, Shape=Rectangular, SingleIcon=False, DisabledState=False / Text / Label»"
          ]
        },
        {
          "node": {
            "id": "58613:29307",
            "name": "[M] BackgroundPlate",
            "type": "INSTANCE",
            "pageName": "Виджет \"Совет\"",
            "path": "[M] WidjetAdvice / Slide=Опцион / Content / [M] BackgroundPlate",
            "visible": true
          },
          "component": {
            "type": "component",
            "name": "[M] BackgroundPlate",
            "key": "e5542ae4d2f93c65ce520258e8060738c38a4976",
            "id": null,
            "library": "Web _ Corp Components",
            "sourceFile": "web/components/web-corp/Web _ Corp Components -- BackgroundPlate.json"
          },
          "variant": {
            "type": "component-variant",
            "name": "Position=Level 2 (inner)",
            "key": "e5542ae4d2f93c65ce520258e8060738c38a4976",
            "id": null,
            "library": "Web _ Corp Components",
            "sourceFile": "web/components/web-corp/Web _ Corp Components -- BackgroundPlate.json"
          },
          "comparisonIssues": []
        },
        {
          "node": {
            "id": "I58613:29307;66402:30707",
            "name": "[M] Style Level 2",
            "type": "INSTANCE",
            "pageName": "Виджет \"Совет\"",
            "path": "[M] WidjetAdvice / Slide=Опцион / Content / [M] BackgroundPlate / [M] Style Level 2",
            "visible": true
          },
          "component": {
            "type": "component",
            "name": "[M] Style Level 2",
            "key": "b2dca6f62c6a8e50f1762cf47f3eeae2a35618c7",
            "id": null,
            "library": "Web _ Corp Components",
            "sourceFile": "web/components/web-corp/Web _ Corp Components -- BackgroundPlate.json"
          },
          "variant": {
            "type": "component-variant",
            "name": "BackgroundColor=base-bg-alt (gray), Type=Primary, Skeleton=False",
            "key": "b2dca6f62c6a8e50f1762cf47f3eeae2a35618c7",
            "id": null,
            "library": "Web _ Corp Components",
            "sourceFile": "web/components/web-corp/Web _ Corp Components -- BackgroundPlate.json"
          },
          "comparisonIssues": []
        },
        {
          "node": {
            "id": "58613:34023",
            "name": "[M] BackgroundPlate",
            "type": "INSTANCE",
            "pageName": "Виджет \"Совет\"",
            "path": "[M] WidjetAdvice / Slide=Опцион / [M] BackgroundPlate",
            "visible": true
          },
          "component": {
            "type": "component",
            "name": "[M] BackgroundPlate",
            "key": "41e2c5c17d573baf32ae78d01b69c0a3d7ba033c",
            "id": null,
            "library": "Web _ Corp Components",
            "sourceFile": "web/components/web-corp/Web _ Corp Components -- BackgroundPlate.json"
          },
          "variant": {
            "type": "component-variant",
            "name": "Position=Level 1 (outer)",
            "key": "41e2c5c17d573baf32ae78d01b69c0a3d7ba033c",
            "id": null,
            "library": "Web _ Corp Components",
            "sourceFile": "web/components/web-corp/Web _ Corp Components -- BackgroundPlate.json"
          },
          "comparisonIssues": []
        },
        {
          "node": {
            "id": "I58613:34023;66402:30705",
            "name": "[M] Style Level 1",
            "type": "INSTANCE",
            "pageName": "Виджет \"Совет\"",
            "path": "[M] WidjetAdvice / Slide=Опцион / [M] BackgroundPlate / [M] Style Level 1",
            "visible": true
          },
          "component": {
            "type": "component",
            "name": "[M] Style Level 1",
            "key": "cdc3f827449db161006abe2250f936b0ee27fafc",
            "id": null,
            "library": "Web _ Corp Components",
            "sourceFile": "web/components/web-corp/Web _ Corp Components -- BackgroundPlate.json"
          },
          "variant": {
            "type": "component-variant",
            "name": "BackgroundColor=base-bg (white), Type=Primary, Skeleton=False",
            "key": "cdc3f827449db161006abe2250f936b0ee27fafc",
            "id": null,
            "library": "Web _ Corp Components",
            "sourceFile": "web/components/web-corp/Web _ Corp Components -- BackgroundPlate.json"
          },
          "comparisonIssues": []
        },
        {
          "node": {
            "id": "58613:29345",
            "name": "[M] Button",
            "type": "INSTANCE",
            "pageName": "Виджет \"Совет\"",
            "path": "[M] WidjetAdvice / Slide=Форвард / Content / Bottom / Controlls / [M] Button",
            "visible": true
          },
          "component": {
            "type": "component",
            "name": "[M] Button",
            "key": "369e0ac445a5a268b6165161f58793685b090f39",
            "id": null,
            "library": "Web _ Core",
            "sourceFile": "web/components/web-core/core/Web _ Core -- Button.json"
          },
          "variant": {
            "type": "component-variant",
            "name": "View=Secondary, Size=32, Shape=Rectangular, SingleIcon=False, DisabledState=False",
            "key": "369e0ac445a5a268b6165161f58793685b090f39",
            "id": null,
            "library": "Web _ Core",
            "sourceFile": "web/components/web-core/core/Web _ Core -- Button.json"
          },
          "comparisonIssues": [
            "Нет данных для скруглений в снапшоте для «View=Secondary, Size=32, Shape=Rectangular, SingleIcon=False, DisabledState=False / Text / Label»"
          ]
        },
        {
          "node": {
            "id": "58613:29352",
            "name": "[M] BackgroundPlate",
            "type": "INSTANCE",
            "pageName": "Виджет \"Совет\"",
            "path": "[M] WidjetAdvice / Slide=Форвард / Content / [M] BackgroundPlate",
            "visible": true
          },
          "component": {
            "type": "component",
            "name": "[M] BackgroundPlate",
            "key": "e5542ae4d2f93c65ce520258e8060738c38a4976",
            "id": null,
            "library": "Web _ Corp Components",
            "sourceFile": "web/components/web-corp/Web _ Corp Components -- BackgroundPlate.json"
          },
          "variant": {
            "type": "component-variant",
            "name": "Position=Level 2 (inner)",
            "key": "e5542ae4d2f93c65ce520258e8060738c38a4976",
            "id": null,
            "library": "Web _ Corp Components",
            "sourceFile": "web/components/web-corp/Web _ Corp Components -- BackgroundPlate.json"
          },
          "comparisonIssues": []
        },
        {
          "node": {
            "id": "I58613:29352;66402:30707",
            "name": "[M] Style Level 2",
            "type": "INSTANCE",
            "pageName": "Виджет \"Совет\"",
            "path": "[M] WidjetAdvice / Slide=Форвард / Content / [M] BackgroundPlate / [M] Style Level 2",
            "visible": true
          },
          "component": {
            "type": "component",
            "name": "[M] Style Level 2",
            "key": "b2dca6f62c6a8e50f1762cf47f3eeae2a35618c7",
            "id": null,
            "library": "Web _ Corp Components",
            "sourceFile": "web/components/web-corp/Web _ Corp Components -- BackgroundPlate.json"
          },
          "variant": {
            "type": "component-variant",
            "name": "BackgroundColor=base-bg-alt (gray), Type=Primary, Skeleton=False",
            "key": "b2dca6f62c6a8e50f1762cf47f3eeae2a35618c7",
            "id": null,
            "library": "Web _ Corp Components",
            "sourceFile": "web/components/web-corp/Web _ Corp Components -- BackgroundPlate.json"
          },
          "comparisonIssues": []
        },
        {
          "node": {
            "id": "58613:34024",
            "name": "[M] BackgroundPlate",
            "type": "INSTANCE",
            "pageName": "Виджет \"Совет\"",
            "path": "[M] WidjetAdvice / Slide=Форвард / [M] BackgroundPlate",
            "visible": true
          },
          "component": {
            "type": "component",
            "name": "[M] BackgroundPlate",
            "key": "41e2c5c17d573baf32ae78d01b69c0a3d7ba033c",
            "id": null,
            "library": "Web _ Corp Components",
            "sourceFile": "web/components/web-corp/Web _ Corp Components -- BackgroundPlate.json"
          },
          "variant": {
            "type": "component-variant",
            "name": "Position=Level 1 (outer)",
            "key": "41e2c5c17d573baf32ae78d01b69c0a3d7ba033c",
            "id": null,
            "library": "Web _ Corp Components",
            "sourceFile": "web/components/web-corp/Web _ Corp Components -- BackgroundPlate.json"
          },
          "comparisonIssues": []
        },
        {
          "node": {
            "id": "I58613:34024;66402:30705",
            "name": "[M] Style Level 1",
            "type": "INSTANCE",
            "pageName": "Виджет \"Совет\"",
            "path": "[M] WidjetAdvice / Slide=Форвард / [M] BackgroundPlate / [M] Style Level 1",
            "visible": true
          },
          "component": {
            "type": "component",
            "name": "[M] Style Level 1",
            "key": "cdc3f827449db161006abe2250f936b0ee27fafc",
            "id": null,
            "library": "Web _ Corp Components",
            "sourceFile": "web/components/web-corp/Web _ Corp Components -- BackgroundPlate.json"
          },
          "variant": {
            "type": "component-variant",
            "name": "BackgroundColor=base-bg (white), Type=Primary, Skeleton=False",
            "key": "cdc3f827449db161006abe2250f936b0ee27fafc",
            "id": null,
            "library": "Web _ Corp Components",
            "sourceFile": "web/components/web-corp/Web _ Corp Components -- BackgroundPlate.json"
          },
          "comparisonIssues": []
        }
      ]
    },
    "themization": {
      "count": 1,
      "items": [
        {
          "node": {
            "id": "58613:29289",
            "name": "Страница: Виджет \"Совет\"",
            "type": "PAGE",
            "pageName": "Виджет \"Совет\"",
            "path": "Виджет \"Совет\"",
            "visible": true
          },
          "kind": "missingThemeMode",
          "recommendation": "Смени темизацию на Corp",
          "component": null
        }
      ]
    }
  }
}
